pinecone_notebooks/__init__.py
pinecone_notebooks/__version__
pinecone_notebooks/colab/__init__.py
pinecone_notebooks/utils.py
pinecone_notebooks-0.1.0.dist-info/LICENSE
pinecone_notebooks-0.1.0.dist-info/METADATA
pinecone_notebooks-0.1.0.dist-info/WHEEL
pinecone_notebooks-0.1.0.dist-info/RECORD
