Metadata-Version: 2.1
Name: pinecone-notebooks
Version: 0.1.0
Summary: Helpers for using Pinecone with notebooks
Home-page: https://www.pinecone.io
License: Apache-2.0
Keywords: Pinecone,vector,database,cloud,jupyter,colab,notebooks
Author: Pinecone Systems, Inc.
Author-email: support@pinecone.io
Requires-Python: >=3.10,<4.0
Classifier: Development Status :: 5 - Production/Stable
Classifier: Intended Audience :: Developers
Classifier: Intended Audience :: Information Technology
Classifier: Intended Audience :: Science/Research
Classifier: Intended Audience :: System Administrators
Classifier: License :: OSI Approved :: Apache Software License
Classifier: Operating System :: OS Independent
Classifier: Programming Language :: Python :: 3
Classifier: Programming Language :: Python :: 3.10
Classifier: Programming Language :: Python :: 3.11
Classifier: Programming Language :: Python :: 3.12
Classifier: Topic :: Database
Classifier: Topic :: Software Development
Classifier: Topic :: Software Development :: Libraries
Classifier: Topic :: Software Development :: Libraries :: Application Frameworks
Classifier: Topic :: Software Development :: Libraries :: Python Modules
Project-URL: Documentation, https://pinecone.io/docs
